pytestbpdb/__init__.py
pytestbpdb/ptbpdb.py
pytest_bpdb-0.1.4.dist-info/METADATA
pytest_bpdb-0.1.4.dist-info/top_level.txt
pytest_bpdb-0.1.4.dist-info/metadata.json
pytest_bpdb-0.1.4.dist-info/RECORD
pytest_bpdb-0.1.4.dist-info/WHEEL
pytest_bpdb-0.1.4.dist-info/DESCRIPTION.rst
pytest_bpdb-0.1.4.dist-info/entry_points.txt
