Metadata-Version: 2.0
Name: pytest-bpdb
Version: 0.1.4
Summary: A py.test plug-in to enable drop to bpdb debugger on test failure.
Home-page: https://github.com/slafs/pytest-bpdb
Author: Sławek Ehlert
Author-email: slafs.e@gmail.com
License: UNKNOWN
Platform: UNKNOWN
Classifier: Development Status :: 2 - Pre-Alpha
Classifier: Environment :: Console
Classifier: Environment :: Plugins
Classifier: Intended Audience :: Developers
Classifier: License :: OSI Approved :: MIT License
Classifier: Operating System :: MacOS :: MacOS X
Classifier: Operating System :: POSIX
Classifier: Programming Language :: Python
Classifier: Topic :: Communications :: Email
Classifier: Topic :: Software Development :: Debuggers
Classifier: Topic :: Software Development :: Testing
Requires-Dist: pytest (>=2.6.3)
Requires-Dist: bpython
